ptracer/__init__.py
ptracer/_lltraceback.cpython-39-darwin.so
ptracer/_ptracer.py
ptracer/_syscall.py
ptracer/ptrace/__init__.py
ptracer/ptrace/_defs_linux.py
ptracer/ptrace/_defs_linux_64.py
ptracer/ptrace/_gen_defs_linux_64.py
ptracer/ptrace/_ptrace.cpython-39-darwin.so
ptracer/ptrace/defs.py
ptracer/ptrace/memory.py
ptracer/ptrace/platform.py
ptracer/ptrace/ptrace.py
ptracer/ptrace/syscalldef.py
ptracer/ptrace/syscalls.py
ptracer-0.6.1.dist-info/LICENSE
ptracer-0.6.1.dist-info/METADATA
ptracer-0.6.1.dist-info/WHEEL
ptracer-0.6.1.dist-info/top_level.txt
ptracer-0.6.1.dist-info/RECORD
