Metadata-Version: 2.1
Name: ptracer
Version: 0.6.1
Summary: On-demand system call tracing for Python programs.
License: Apache License, Version 2.0
Platform: POSIX
Classifier: License :: OSI Approved :: Apache Software License
Classifier: Intended Audience :: Developers
Classifier: Programming Language :: Python
Classifier: Programming Language :: Python :: 3
Classifier: Operating System :: POSIX :: Linux
Classifier: Development Status :: 4 - Beta
Provides: ptracer
License-File: LICENSE
